ailite/__init__.py
ailite/_ai_validator.py
ailite/model/__init__.py
ailite/model/_models.py
ailite-7.0.11.dist-info/LICENSE
ailite-7.0.11.dist-info/METADATA
ailite-7.0.11.dist-info/WHEEL
ailite-7.0.11.dist-info/RECORD
