Metadata-Version: 2.1
Name: ailite
Version: 7.0.11
Summary: All popular Framework HF integration kit
Home-page: https://github.com/santhosh/
License: MIT
Author: Kammari Santhosh
Requires-Python: >=3.10,<4.0
Classifier: License :: OSI Approved :: MIT License
Classifier: Programming Language :: Python :: 3
Classifier: Programming Language :: Python :: 3.10
Classifier: Programming Language :: Python :: 3.11
Classifier: Programming Language :: Python :: 3.12
Classifier: Programming Language :: Python :: 3.13
Requires-Dist: langchain_ollama (>=0.2.2,<0.3.0)
Requires-Dist: visionlite (>=0.1.58,<0.2.0)
Requires-Dist: wordllama (>=0.3.7,<0.4.0)
Project-URL: Repository, https://github.com/santhosh/
